README.txt
setup.cfg
setup.py
Products/__init__.py
Products.highlighter.egg-info/PKG-INFO
Products.highlighter.egg-info/SOURCES.txt
Products.highlighter.egg-info/dependency_links.txt
Products.highlighter.egg-info/entry_points.txt
Products.highlighter.egg-info/namespace_packages.txt
Products.highlighter.egg-info/not-zip-safe
Products.highlighter.egg-info/paster_plugins.txt
Products.highlighter.egg-info/requires.txt
Products.highlighter.egg-info/top_level.txt
Products/highlighter/__init__.py
Products/highlighter/configure.zcml
Products/highlighter/tests.py
Products/highlighter/browser/__init__.py
Products/highlighter/browser/analytics.pt
Products/highlighter/browser/configure.zcml
Products/highlighter/browser/controlpanel.py
Products/highlighter/browser/highlighter.css
Products/highlighter/browser/highlighteranalytics.pt
Products/highlighter/browser/highlighteranalytics.py
Products/highlighter/browser/highlighterenablemessage.pt
Products/highlighter/browser/highlighterenablemessage.py
Products/highlighter/browser/highlighterfooter.pt
Products/highlighter/browser/highlighterfooter.py
Products/highlighter/browser/highlightermanagement.pt
Products/highlighter/profiles/default/controlpanel.xml
Products/highlighter/profiles/default/cssregistry.xml
Products/highlighter/profiles/default/metadata.xml
Products/highlighter/profiles/default/propertiestool.xml
docs/HISTORY.txt
docs/INSTALL.txt
docs/LICENSE.GPL
docs/LICENSE.txt