Metadata-Version: 1.0
Name: Products.highlighter
Version: 1.0
Summary: Highlight text in your plone site and see what others are highlighting as well.
Home-page: http://svn.plone.org/svn/collective/
Author: UNKNOWN
Author-email: UNKNOWN
License: GPL
Platform: UNKNOWN
Classifier: Framework :: Plone
Classifier: Programming Language :: Python
